apolo_kube_client/__init__.py
apolo_kube_client/_admissionregistration_k8s_io_v1.py
apolo_kube_client/_apiextensions_k8s_io_v1.py
apolo_kube_client/_apolo_waiters.py
apolo_kube_client/_apps_v1.py
apolo_kube_client/_attr.py
apolo_kube_client/_base_resource.py
apolo_kube_client/_batch_v1.py
apolo_kube_client/_client.py
apolo_kube_client/_config.py
apolo_kube_client/_constants.py
apolo_kube_client/_core.py
apolo_kube_client/_core_v1.py
apolo_kube_client/_crd_models.py
apolo_kube_client/_discovery_k8s_io_v1.py
apolo_kube_client/_errors.py
apolo_kube_client/_models/__init__.py
apolo_kube_client/_models/admissionregistration_v1_service_reference.py
apolo_kube_client/_models/admissionregistration_v1_webhook_client_config.py
apolo_kube_client/_models/apiextensions_v1_service_reference.py
apolo_kube_client/_models/apiextensions_v1_webhook_client_config.py
apolo_kube_client/_models/apiregistration_v1_service_reference.py
apolo_kube_client/_models/authentication_v1_token_request.py
apolo_kube_client/_models/base.py
apolo_kube_client/_models/core_v1_endpoint_port.py
apolo_kube_client/_models/core_v1_event.py
apolo_kube_client/_models/core_v1_event_list.py
apolo_kube_client/_models/core_v1_event_series.py
apolo_kube_client/_models/core_v1_resource_claim.py
apolo_kube_client/_models/discovery_v1_endpoint_port.py
apolo_kube_client/_models/events_v1_event.py
apolo_kube_client/_models/events_v1_event_list.py
apolo_kube_client/_models/events_v1_event_series.py
apolo_kube_client/_models/flowcontrol_v1_subject.py
apolo_kube_client/_models/rbac_v1_subject.py
apolo_kube_client/_models/resource_v1_resource_claim.py
apolo_kube_client/_models/storage_v1_token_request.py
apolo_kube_client/_models/utils.py
apolo_kube_client/_models/v1_affinity.py
apolo_kube_client/_models/v1_aggregation_rule.py
apolo_kube_client/_models/v1_allocated_device_status.py
apolo_kube_client/_models/v1_allocation_result.py
apolo_kube_client/_models/v1_api_group.py
apolo_kube_client/_models/v1_api_group_list.py
apolo_kube_client-25.11.5.dist-info/LICENSE
apolo_kube_client-25.11.5.dist-info/METADATA
apolo_kube_client-25.11.5.dist-info/WHEEL
apolo_kube_client-25.11.5.dist-info/RECORD
