Metadata-Version: 2.3
Name: apolo-kube-client
Version: 25.11.5
Summary: Apolo internal client for kubernetes API
License: Proprietary
Author: apolo.us
Requires-Python: >=3.13,<4.0
Classifier: License :: Other/Proprietary License
Classifier: Programming Language :: Python :: 3
Classifier: Programming Language :: Python :: 3.13
Requires-Dist: aiohttp (>=3.12.9)
Requires-Dist: cachetools (>=5.3.3)
Requires-Dist: multidict (>=6)
Requires-Dist: pydantic (>=2.12.3,<3.0.0)
Requires-Dist: pyyaml (>=6.0.3,<7.0.0)
Requires-Dist: yarl (>=1.20)
